<odoo>
  <data>
    <!-- explicit list view definition -->
<!--
    <record model="ir.ui.view" id="wb_wms_self_diagnostic_tool.list">
      <field name="name">wb_wms_self_diagnostic_tool list</field>
      <field name="model">wb_wms_self_diagnostic_tool.wb_wms_self_diagnostic_tool</field>
      <field name="arch" type="xml">
        <tree>
          <field name="name"/>
          <field name="value"/>
          <field name="value2"/>
        </tree>
      </field>
    </record>
-->

    <!-- actions opening views on models -->
<!--
    <record model="ir.actions.act_window" id="wb_wms_self_diagnostic_tool.action_window">
      <field name="name">wb_wms_self_diagnostic_tool window</field>
      <field name="res_model">wb_wms_self_diagnostic_tool.wb_wms_self_diagnostic_tool</field>
      <field name="view_mode">tree,form</field>
    </record>
-->

    <!-- server action to the one above -->
<!--
    <record model="ir.actions.server" id="wb_wms_self_diagnostic_tool.action_server">
      <field name="name">wb_wms_self_diagnostic_tool server</field>
      <field name="model_id" ref="model_wb_wms_self_diagnostic_tool_wb_wms_self_diagnostic_tool"/>
      <field name="state">code</field>
      <field name="code">
        action = {
          "type": "ir.actions.act_window",
          "view_mode": "tree,form",
          "res_model": model._name,
        }
      </field>
    </record>
-->

    <!-- Top menu item -->
<!--
    <menuitem name="wb_wms_self_diagnostic_tool" id="wb_wms_self_diagnostic_tool.menu_root"/>
-->
    <!-- menu categories -->
<!--
    <menuitem name="Menu 1" id="wb_wms_self_diagnostic_tool.menu_1" parent="wb_wms_self_diagnostic_tool.menu_root"/>
    <menuitem name="Menu 2" id="wb_wms_self_diagnostic_tool.menu_2" parent="wb_wms_self_diagnostic_tool.menu_root"/>
-->
    <!-- actions -->
<!--
    <menuitem name="List" id="wb_wms_self_diagnostic_tool.menu_1_list" parent="wb_wms_self_diagnostic_tool.menu_1"
              action="wb_wms_self_diagnostic_tool.action_window"/>
    <menuitem name="Server to list" id="wb_wms_self_diagnostic_tool" parent="wb_wms_self_diagnostic_tool.menu_2"
              action="wb_wms_self_diagnostic_tool.action_server"/>
-->
  </data>
</odoo>